<?xml version="1.0" encoding="utf-8" standalone="yes" ?>
<T3locallangExt>
	<data type="array">
		<languageKey index="ru" type="array">
			<label index="mlang_tabs_tab">Справка по TypoScript</label>
			<label index="mlang_labels_tabdescr">Справочная информация по объектам TSref, Странице TSconfig и Пользователю TSconfig. Также дает возможность администрации перестроить всю сетевую справку по TypoScript, вместе с руководствами всех установленных расширений (включая основную документацию, если установлено).</label>
			<label index="mlang_labels_tablabel">Справка по TypoScript</label>
		</languageKey>
	</data>
	<orig_hash type="array">
		<languageKey index="ru" type="array">
			<label index="mlang_tabs_tab" type="integer">55592368</label>
			<label index="mlang_labels_tabdescr" type="integer">186004151</label>
			<label index="mlang_labels_tablabel" type="integer">55592368</label>
		</languageKey>
	</orig_hash>
	<orig_text type="array">
		<languageKey index="ru" type="array">
			<label index="mlang_tabs_tab">TypoScript Help</label>
			<label index="mlang_labels_tabdescr">Object reference for TSref, Page TSconfig and User TSconfig. Also enables the admin to rebuild the whole TypoScript online reference with the manuals of all installed extensions (including core documentation, if installed).</label>
			<label index="mlang_labels_tablabel">TypoScript Help</label>
		</languageKey>
	</orig_text>
</T3locallangExt>