<?xml version="1.0" encoding="utf-8" standalone="yes" ?>
<T3locallangExt>
	<data type="array">
		<languageKey index="fi" type="array">
			<label index="wiz_crMany">Luo useita sivuja</label>
			<label index="wiz_W">W!</label>
			<label index="wiz_newPages">Luo uusia sivuja</label>
			<label index="wiz_newPages_page">Sivu</label>
			<label index="wiz_newPages_currentMenu">Uusi sivurakenne</label>
			<label index="wiz_newPages_errorMsg1">Sinulla ei ole oikeuksia luoda alasivuja tälle sivulle!</label>
			<label index="wiz_newPages_lCreate">Luo sivuja</label>
			<label index="wiz_newPages_listEnd">Sijoita uudet sivut alemassa olevien alasivujen jälkeen</label>
			<label index="wiz_newPages_hidePages">Piilota uudet sivut</label>
			<label index="wiz_newPages_lCreate_msg1">Olet aikeissa luoda lukuisia uusia sivuja. Oletko varma, että haluat jatkaa ?</label>
			<label index="wiz_newPages_lReset">Tyhjää kentät</label>
			<label index="wiz_newPages_noCreate">Sivuja ei luotu!</label>
			<label index="wiz_newPages_helpText">Täällä voit luoda kerralla joukon uusia, tyhjiä  sivuja Keino on käytännöllinen halutessasi luoda nopeasti sivurakenteen uuteen sivustoon.&lt;br /&gt;Annat vain otsikot uusille sivuille joita tarvitset. Ainoastaan ne joiden kentät täytät luodaan sivuiksi.</label>
		</languageKey>
	</data>
	<orig_hash type="array">
		<languageKey index="fi" type="array">
			<label index="wiz_crMany" type="integer">69436019</label>
			<label index="wiz_W" type="integer">247242126</label>
			<label index="wiz_newPages" type="integer">203564147</label>
			<label index="wiz_newPages_page" type="integer">26464201</label>
			<label index="wiz_newPages_currentMenu" type="integer">1353175</label>
			<label index="wiz_newPages_helpText" type="integer">257879061</label>
			<label index="wiz_newPages_errorMsg1" type="integer">252016009</label>
			<label index="wiz_newPages_lCreate" type="integer">246594352</label>
			<label index="wiz_newPages_listEnd" type="integer">58585614</label>
			<label index="wiz_newPages_hidePages" type="integer">71614542</label>
			<label index="wiz_newPages_lCreate_msg1" type="integer">197760570</label>
			<label index="wiz_newPages_lReset" type="integer">3106134</label>
			<label index="wiz_newPages_noCreate" type="integer">151121547</label>
		</languageKey>
	</orig_hash>
	<orig_text type="array">
		<languageKey index="fi" type="array">
		</languageKey>
	</orig_text>
</T3locallangExt>